mosaik_csv.py
mosaik_csv_writer.py
mosaik_csv-2.0.1.dist-info/AUTHORS.txt
mosaik_csv-2.0.1.dist-info/LICENSE.txt
mosaik_csv-2.0.1.dist-info/METADATA
mosaik_csv-2.0.1.dist-info/WHEEL
mosaik_csv-2.0.1.dist-info/entry_points.txt
mosaik_csv-2.0.1.dist-info/top_level.txt
mosaik_csv-2.0.1.dist-info/RECORD
